{
  "apiType": "stageMode",
  "buildOption": {
    "resOptions": {
      "copyCodeResource": {
        "enable": false
      }
    }
  },
  "buildOptionSet": [
    {
      "name": "debug",
      "arkOptions": {
        "obfuscation": {
          "ruleOptions": {
            "enable": false
          }
        }
      }
    },
    {
      "name": "release",
      "arkOptions": {
        "obfuscation": {
          "ruleOptions": {
            "enable": true,
            "files": [
              "./obfuscation-rules.txt"
            ]
          }
        }
      }
    }
  ],
  "modules": [
    {
      "name": "raytv",
      "srcPath": "./src",
      "targets": [
        {
          "name": "default",
          "applyToProducts": [
            "default"
          ]
        }
      ]
    }
  ],
  "targets": [
    {
      "name": "default"
    },
    {
      "name": "ohosTest"
    }
  ]
}